napari_nninteractive/__init__.py
napari_nninteractive/napari.yaml
napari_nninteractive/widget_controls.py
napari_nninteractive/widget_gui.py
napari_nninteractive/widget_main.py
napari_nninteractive/controls/__init__.py
napari_nninteractive/controls/bbox_controls.py
napari_nninteractive/controls/lasso_controls.py
napari_nninteractive/controls/point_controls.py
napari_nninteractive/controls/scribble_controls.py
napari_nninteractive/layers/__init__.py
napari_nninteractive/layers/abstract_layer.py
napari_nninteractive/layers/bbox_layer.py
napari_nninteractive/layers/lasso_layer.py
napari_nninteractive/layers/point_layer.py
napari_nninteractive/layers/scribble_layer.py
napari_nninteractive/utils/__init__.py
napari_nninteractive/utils/affine.py
napari_nninteractive/utils/utils.py
napari_nninteractive-1.0.5.dist-info/licenses/LICENSE
napari_nninteractive-1.0.5.dist-info/METADATA
napari_nninteractive-1.0.5.dist-info/WHEEL
napari_nninteractive-1.0.5.dist-info/entry_points.txt
napari_nninteractive-1.0.5.dist-info/top_level.txt
napari_nninteractive-1.0.5.dist-info/RECORD
