Metadata-Version: 2.4
Name: napari-nninteractive
Version: 1.0.5
Summary: nnInteractive plugin for Napari
Author: Lars Krämer, Fabian Isensee, Maximilian Rokuss
Author-email: lars.kraemer@dkfz-heidelberg.de, f.isensee@dkfz-heidelberg.de, maximilian.rokuss@dkfz-heidelberg.de
License: 
Project-URL: Homepage, https://github.com/MIC-DKFZ/napari-nninteractive
Project-URL: Code, https://github.com/MIC-DKFZ/napari-nninteractive
Classifier: Development Status :: 2 - Pre-Alpha
Classifier: Framework :: napari
Classifier: Intended Audience :: Developers
Classifier: License :: OSI Approved :: Apache Software License
Classifier: Operating System :: OS Independent
Classifier: Programming Language :: Python
Classifier: Programming Language :: Python :: 3
Classifier: Programming Language :: Python :: 3 :: Only
Classifier: Programming Language :: Python :: 3.9
Classifier: Programming Language :: Python :: 3.10
Classifier: Programming Language :: Python :: 3.11
Classifier: Programming Language :: Python :: 3.12
Classifier: Topic :: Scientific/Engineering :: Image Processing
Requires-Python: >=3.10
License-File: LICENSE
Requires-Dist: torch
Requires-Dist: numpy
Requires-Dist: qtpy
Requires-Dist: napari-nifti
Requires-Dist: huggingface_hub
Requires-Dist: hf_transfer
Requires-Dist: nnInteractive>=1.0.0
Requires-Dist: napari_toolkit
Provides-Extra: testing
Requires-Dist: tox; extra == "testing"
Requires-Dist: pytest; extra == "testing"
Requires-Dist: pytest-cov; extra == "testing"
Requires-Dist: pytest-qt; extra == "testing"
Requires-Dist: napari; extra == "testing"
Requires-Dist: pyqt5; extra == "testing"
Dynamic: license-file
